LICENSE
MANIFEST.in
README.rst
setup.cfg
setup.py
objectifier/__init__.py
objectifier/metadata.py
objectifier/objectifier.py
objectifier/tests.py
objectifier.egg-info/PKG-INFO
objectifier.egg-info/SOURCES.txt
objectifier.egg-info/dependency_links.txt
objectifier.egg-info/top_level.txt