Metadata-Version: 1.0
Name: objectifier
Version: 1.3.0
Summary: Objectifier makes it easy to inspect and traverse Python objects.
Home-page: https://github.com/elmcitylabs/objectifier
Author: Dan Loewenherz
Author-email: dan@dlo.me
License: Apache 2.0
Platform: UNKNOWN
